linux/__init__.py
linux/change_mac.py
windows/__init__.py
windows/change_mac.py
macrenew-1.0.0.dist-info/LICENSE.txt
macrenew-1.0.0.dist-info/METADATA
macrenew-1.0.0.dist-info/WHEEL
macrenew-1.0.0.dist-info/top_level.txt
macrenew-1.0.0.dist-info/RECORD
