Metadata-Version: 2.1
Name: macrenew
Version: 1.0.0
Summary: A simple Python script to change the mac address of your machine. Current only working on Linux.
Author: Andre Buck
Classifier: Programming Language :: Python :: 3
Classifier: License :: OSI Approved :: MIT License
Classifier: Operating System :: OS Independent
Requires-Python: >=3.6
License-File: LICENSE.txt
